ppt2txt/__init__.py
ppt2txt/__main__.py
ppt2txt/ppt2txt.py
ppt2txt-0.1.0.dist-info/LICENSE
ppt2txt-0.1.0.dist-info/METADATA
ppt2txt-0.1.0.dist-info/WHEEL
ppt2txt-0.1.0.dist-info/entry_points.txt
ppt2txt-0.1.0.dist-info/top_level.txt
ppt2txt-0.1.0.dist-info/RECORD
