Metadata-Version: 2.1
Name: ppt2txt
Version: 0.1.0
Summary: A pure python based utility to extract text from PPT files.
Author: Mattia Mancassola
License: MIT License
Project-URL: Homepage, https://github.com/mett29/ppt2txt
Keywords: python,ppt,binary,extract,parse
Classifier: License :: OSI Approved :: MIT License
Classifier: Programming Language :: Python :: 3
Classifier: Topic :: Software Development :: Build Tools
Classifier: Development Status :: 4 - Beta
Requires-Python: >=3.8
License-File: LICENSE
Requires-Dist: olefile ==0.46
